github_pr_analyzer-3.0.7.dist-info/licenses/LICENSE
src/__init__.py
src/ai_analyzer.py
src/cli.py
src/commit_collector.py
src/config.py
src/diff_viewer.py
src/matcher.py
src/pr_collector.py
src/pr_exporter.py
src/smart_search_analyzer.py
src/utils.py
github_pr_analyzer-3.0.7.dist-info/METADATA
github_pr_analyzer-3.0.7.dist-info/WHEEL
github_pr_analyzer-3.0.7.dist-info/entry_points.txt
github_pr_analyzer-3.0.7.dist-info/top_level.txt
github_pr_analyzer-3.0.7.dist-info/RECORD
