Metadata-Version: 2.4
Name: github-pr-analyzer
Version: 3.0.7
Summary: Intelligent tool for collecting, analyzing, and summarizing GitHub Pull Requests and commits
Home-page: https://github.com/yourusername/github-pr-analyzer
Author: GitHub PR Analyzer Team
Classifier: Development Status :: 5 - Production/Stable
Classifier: Intended Audience :: Developers
Classifier: Topic :: Software Development :: Version Control :: Git
Classifier: License :: OSI Approved :: MIT License
Classifier: Programming Language :: Python :: 3
Classifier: Programming Language :: Python :: 3.8
Classifier: Programming Language :: Python :: 3.9
Classifier: Programming Language :: Python :: 3.10
Classifier: Programming Language :: Python :: 3.11
Classifier: Programming Language :: Python :: 3.12
Requires-Python: >=3.8
License-File: LICENSE
Requires-Dist: click>=8.1.0
Requires-Dist: rich>=13.0.0
Requires-Dist: requests>=2.31.0
Requires-Dist: gitpython>=3.1.40
Requires-Dist: python-dateutil>=2.8.2
Requires-Dist: fuzzywuzzy>=0.18.0
Requires-Dist: python-levenshtein>=0.21.0
Dynamic: author
Dynamic: classifier
Dynamic: description
Dynamic: description-content-type
Dynamic: home-page
Dynamic: license-file
Dynamic: requires-dist
Dynamic: requires-python
Dynamic: summary
